LICENSE
MANIFEST.in
README.rst
setup.py
PyVSL/VSLite_v2_3.m
PyVSL/__init__.py
PyVSL/betarnd.m
PyVSL/binornd.m
PyVSL/core.py
PyVSL/estimate_vslite_params_v2_3.m
PyVSL/leakybucket_monthly.m
PyVSL/nanmean.m
PyVSL/nanstd.m
PyVSL/nanvar.m
PyVSL/rng.m
PyVSL/unifrnd.m
PyVSL/utils.py
PyVSL/wrapper.py
PyVSL.egg-info/PKG-INFO
PyVSL.egg-info/SOURCES.txt
PyVSL.egg-info/dependency_links.txt
PyVSL.egg-info/requires.txt
PyVSL.egg-info/top_level.txt