Metadata-Version: 2.1
Name: PyVSL
Version: 0.2.0
Summary: VS-Lite in Python
Home-page: https://github.com/fzhu2e/PyVSL
Author: Feng Zhu
Author-email: fengzhu@ucar.edu
License: GPL-3.0 License
Keywords: Proxy System Modeling,Tree-ring Width
Classifier: Programming Language :: Python :: 3.9
Classifier: Programming Language :: Python :: 3.10
License-File: LICENSE
